latpy/__init__.py
latpy/common.py
latpy/latpy.py
latpy/utils.py
latpy-0.0.3.dist-info/LICENSE
latpy-0.0.3.dist-info/METADATA
latpy-0.0.3.dist-info/WHEEL
latpy-0.0.3.dist-info/entry_points.txt
latpy-0.0.3.dist-info/top_level.txt
latpy-0.0.3.dist-info/RECORD
