Metadata-Version: 2.1
Name: latpy
Version: 0.0.3
Summary: Outcomes benefits python toolbox with mapping capabilities
Author-email: Vance Russell <vance@3point.xyz>
License: MIT License
Project-URL: Homepage, https://github.com/VRConservation/latpy
Keywords: latpy
Classifier: Intended Audience :: Developers
Classifier: License :: OSI Approved :: MIT License
Classifier: Natural Language :: English
Classifier: Programming Language :: Python :: 3.8
Classifier: Programming Language :: Python :: 3.9
Classifier: Programming Language :: Python :: 3.10
Classifier: Programming Language :: Python :: 3.11
Classifier: Programming Language :: Python :: 3.12
Requires-Python: >=3.8
License-File: LICENSE
Requires-Dist: numpy
Requires-Dist: ipyleaflet
Requires-Dist: pandas
Provides-Extra: all
Requires-Dist: latpy[extra] ; extra == 'all'
Provides-Extra: extra
Requires-Dist: pandas ; extra == 'extra'
